cmitai/main.py
cmitai-0.1.0.dist-info/licenses/LICENSE
cmitai-0.1.0.dist-info/METADATA
cmitai-0.1.0.dist-info/WHEEL
cmitai-0.1.0.dist-info/entry_points.txt
cmitai-0.1.0.dist-info/top_level.txt
cmitai-0.1.0.dist-info/RECORD
