Metadata-Version: 2.4
Name: cmitai
Version: 0.1.0
Summary: Generate Git commit messages using LLMs (OpenAI or Google Gemini)
Author: Oziel Senior
License: MIT
Keywords: git,commit,ai,cli
Requires-Python: >=3.10
License-File: LICENSE
Requires-Dist: gitpython>=3.1.44
Requires-Dist: google-generativeai>=0.8.5
Requires-Dist: openai>=1.82.0
Requires-Dist: typer>=0.15.4
Dynamic: license-file
